{
  "edge": {
    "n":4,
    "0":{
      "x": 0,
      "y": 0,
      "z": 0
    },

    "2":{
      "x": 0.5,
      "y": 0,
      "z": 0.5
    },

    "1":{
      "x": 0.5,
      "y": 0.5,
      "z": 0
    },

    "3":{
      "x": 0,
      "y": 0.5,
      "z": 0.5
    }
  },

  "size":{
    "x":3,
    "y":3,
    "z":3
  },
    
  "initial_potencial_features":{
    "A1":0.0376,
    "A0":0.7,
  "qsi":1.070,
  "p":16.999,
  "q":1.189
  
  },

  "type":1,

  "initial_energy":{
    "a":4.085,
    "E_c":-2.96,
    "B":1.08,
    "C11":1.32,
    "C12":0.97,
    "C44":0.51,
    "E_sol":0.497,
    "E_in":0.22,
    "E_on":-0.36
    
  },

  "optimizer_params":{
    "step" : 20,
    "epoch": 1,
    "lambda": 2,
    "residual":0.0001,
    "epsilon": 0.005,
    "delta": 0.05
},

"e_coh_B": 5.31,

"material_base": "Ag(001)",
"material_impurity": "V"
  
  }
 


